bets/__init__.py
bets/main.py
bets/__pycache__/__init__.cpython-38.pyc
bets/model/__init__.py
bets/model/match.py
bets/model/matches.py
bets/model/scenario.py
bets/model/scenarios.py
bets/model/__pycache__/__init__.cpython-38.pyc
bets/model/__pycache__/matches.cpython-38.pyc
bets/model/__pycache__/scenarios.cpython-38.pyc
bets/model/stats/__init__.py
bets/model/stats/abstract_stats.py
bets/model/stats/constants.py
bets/model/stats/outcome_stats.py
bets/model/stats/ratio_stats.py
bets/model/stats/reports.py
bets/model/stats/score_stats.py
bets/model/stats/stats_collection.py
bets/model/stats/__pycache__/__init__.cpython-38.pyc
bets/model/stats/__pycache__/abstract_stats.cpython-38.pyc
bets/model/stats/__pycache__/constants.cpython-38.pyc
bets/model/stats/__pycache__/outcome_stats.cpython-38.pyc
bets/model/stats/__pycache__/ratio_stats.cpython-38.pyc
bets/model/stats/__pycache__/reports.cpython-38.pyc
bets/model/stats/__pycache__/score_stats.cpython-38.pyc
bets/model/stats/__pycache__/stats_collection.cpython-38.pyc
bets/program_io/__init__.py
bets/program_io/matches_input.py
bets/program_io/matches_output.py
bets/program_io/scenarios_output.py
bets/ui/__init__.py
bets/ui/bets_app.py
bets/ui/constants.py
bets/ui/matches_observable.py
bets/ui/menu_bar.py
bets/ui/table_frame.py
bets/ui/__pycache__/__init__.cpython-38.pyc
bets/ui/__pycache__/bets_app.cpython-38.pyc
bets/ui/__pycache__/constants.cpython-38.pyc
bets/ui/__pycache__/matches_observable.cpython-38.pyc
bets/ui/__pycache__/menu_bar.cpython-38.pyc
bets/ui/__pycache__/table_frame.cpython-38.pyc
bets/ui/matches_tab/__init__.py
bets/ui/matches_tab/manual_match_input_frame.py
bets/ui/matches_tab/matches_tab_frame.py
bets/ui/matches_tab/matches_table_frame.py
bets/ui/matches_tab/pasted_matches_input.py
bets/ui/matches_tab/__pycache__/__init__.cpython-38.pyc
bets/ui/matches_tab/__pycache__/manual_match_input_frame.cpython-38.pyc
bets/ui/matches_tab/__pycache__/matches_tab_frame.cpython-38.pyc
bets_cli-4.0.1.dist-info/AUTHORS.rst
bets_cli-4.0.1.dist-info/LICENSE.txt
bets_cli-4.0.1.dist-info/METADATA
bets_cli-4.0.1.dist-info/WHEEL
bets_cli-4.0.1.dist-info/entry_points.txt
bets_cli-4.0.1.dist-info/top_level.txt
bets_cli-4.0.1.dist-info/RECORD
