Metadata-Version: 2.1
Name: bets-cli
Version: 4.0.1
Summary: CLI to assist football bets
Home-page: https://github.com/nachereshata/bets-cli.git
Author: nachereshata
Author-email: nachereshata@gmail.com
License: mit
Platform: any
Classifier: Development Status :: 4 - Beta
Classifier: Environment :: Console
Classifier: Environment :: Win32 (MS Windows)
Classifier: Environment :: X11 Applications
Classifier: License :: OSI Approved :: MIT License
Classifier: Programming Language :: Python
Classifier: Operating System :: Microsoft :: Windows
Classifier: Operating System :: POSIX :: Linux
Classifier: Programming Language :: Python :: 3 :: Only
Classifier: Topic :: Utilities
Requires-Python: >=3.6.5
Requires-Dist: tabulate
Requires-Dist: more-itertools
Requires-Dist: pandas
Requires-Dist: xlrd
Requires-Dist: xlwt
Provides-Extra: testing
Requires-Dist: pytest ; extra == 'testing'
Requires-Dist: pytest-cov ; extra == 'testing'
Requires-Dist: mock ; extra == 'testing'
Requires-Dist: flake8 ; extra == 'testing'
Requires-Dist: sphinx ; extra == 'testing'
